ding_robot_moon/__init__.py
ding_robot_moon/custom_robot.py
ding_robot_moon-0.1.2.dist-info/licenses/LICENSE
ding_robot_moon-0.1.2.dist-info/METADATA
ding_robot_moon-0.1.2.dist-info/WHEEL
ding_robot_moon-0.1.2.dist-info/top_level.txt
ding_robot_moon-0.1.2.dist-info/RECORD
