Metadata-Version: 2.4
Name: ding_robot_moon
Version: 0.1.2
Summary: My Python SDK
Author-email: moon <lianjiao20@gmail.com>
Project-URL: Homepage, https://github.com/lianjiao20-gif/ding-robot
Project-URL: Repository, https://github.com/lianjiao20-gif/ding-robot
Requires-Python: >=3.8
License-File: LICENSE
Requires-Dist: requests>=2.25.0
Dynamic: license-file
